qmenta/__init__.py
qmenta/sdk/__init__.py
qmenta/sdk/client.py
qmenta/sdk/communication.py
qmenta/sdk/context.py
qmenta/sdk/directory_utils.py
qmenta/sdk/executor.py
qmenta/sdk/init.py
qmenta/sdk/log_capture.py
qmenta/sdk/make_entrypoint.py
qmenta/sdk/bids/__init__.py
qmenta/sdk/bids/make_entrypoint.py
qmenta/sdk/bids/wrapper.py
qmenta/sdk/local/__init__.py
qmenta/sdk/local/client.py
qmenta/sdk/local/context.py
qmenta/sdk/local/executor.py
qmenta/sdk/local/parse_settings.py
qmenta/sdk/tool_maker/__init__.py
qmenta/sdk/tool_maker/context.py
qmenta/sdk/tool_maker/file_filter.py
qmenta/sdk/tool_maker/inputs.py
qmenta/sdk/tool_maker/integration_ui.py
qmenta/sdk/tool_maker/integration_workflow_ui.py
qmenta/sdk/tool_maker/launch_gui.py
qmenta/sdk/tool_maker/make_files.py
qmenta/sdk/tool_maker/modalities.py
qmenta/sdk/tool_maker/outputs.py
qmenta/sdk/tool_maker/run_test_docker.py
qmenta/sdk/tool_maker/tool_maker.py
qmenta/sdk/tool_maker/templates_tool_maker/Dockerfile_schema
qmenta/sdk/tool_maker/templates_tool_maker/description_schema
qmenta/sdk/tool_maker/templates_tool_maker/qmenta.png
qmenta/sdk/tool_maker/templates_tool_maker/test_tool_schema
qmenta/sdk/tool_maker/templates_tool_maker/tool_schema
qmenta_sdk_lib-2.0.dist-info/METADATA
qmenta_sdk_lib-2.0.dist-info/WHEEL
qmenta_sdk_lib-2.0.dist-info/entry_points.txt
qmenta_sdk_lib-2.0.dist-info/top_level.txt
qmenta_sdk_lib-2.0.dist-info/RECORD
