Metadata-Version: 2.1
Name: qmenta_sdk_lib
Version: 2.0
Summary: The QMENTA Python SDK offers a simple connector API that allows developers to integrate their tools with the QMENTA platform.
Home-page: https://qmenta.com
Author: QMENTA
Author-email: dev@qmenta.com
Classifier: Development Status :: 5 - Production/Stable
Classifier: Intended Audience :: Developers
Classifier: License :: OSI Approved :: MIT License
Classifier: Programming Language :: Python
Classifier: Topic :: Scientific/Engineering :: Bio-Informatics
Requires-Dist: enum-compat
Requires-Dist: humanfriendly
Requires-Dist: future
Requires-Dist: requests
Requires-Dist: qmenta-client
Requires-Dist: flake8
Requires-Dist: sphinx
Requires-Dist: pytest-cov
Requires-Dist: pytest
Requires-Dist: PySimpleGui
Requires-Dist: sphinx-rtd-theme
